tzif_parser/__init__.py
tzif_parser/models.py
tzif_parser/posix.py
tzif_parser/tz_transition.py
tzif_parser/tzif.py
tzif_parser/tzif_body.py
tzif_parser/tzif_header.py
tzif_parser-0.0.16.dist-info/licenses/LICENSE
tzif_parser-0.0.16.dist-info/METADATA
tzif_parser-0.0.16.dist-info/WHEEL
tzif_parser-0.0.16.dist-info/top_level.txt
tzif_parser-0.0.16.dist-info/RECORD
