Metadata-Version: 2.4
Name: tzif-parser
Version: 0.0.16
Summary: Easily parse Time Zone Information Format (TZif) files.
Home-page: https://github.com/MasonFlint44/tzif-parser
Author: Mason Flint
Author-email: masonflint44@gmail.com
Project-URL: Bug Tracker, https://github.com/MasonFlint44/tzif-parser/issues
Classifier: Programming Language :: Python :: 3
Classifier: License :: OSI Approved :: MIT License
Classifier: Operating System :: OS Independent
Classifier: Development Status :: 3 - Alpha
Classifier: Intended Audience :: Developers
Requires-Python: >=3.10
License-File: LICENSE
Dynamic: license-file
